webtest_sanic/__init__.py
webtest_sanic/app.py
webtest_sanic/utils.py
webtest_sanic-0.4.2.dist-info/LICENSE
webtest_sanic-0.4.2.dist-info/METADATA
webtest_sanic-0.4.2.dist-info/NOTICE.md
webtest_sanic-0.4.2.dist-info/WHEEL
webtest_sanic-0.4.2.dist-info/top_level.txt
webtest_sanic-0.4.2.dist-info/RECORD
