Metadata-Version: 2.1
Name: webtest-sanic
Version: 0.4.2
Summary: webtest-sanic provides integration of WebTest with Sanic applications
Home-page: https://github.com/EndurantDevs/webtest_sanic
Author: Endurant Devs, Dmytro Nikolayev
Author-email: info@endurantdev.com
License: MIT
Keywords: webtest-sanic webtest sanic testing wsgi asyncio
Platform: UNKNOWN
Classifier: Intended Audience :: Developers
Classifier: Environment :: Web Environment
Classifier: License :: OSI Approved :: MIT License
Classifier: Natural Language :: English
Classifier: Programming Language :: Python :: 3
Classifier: Programming Language :: Python :: 3.6
Classifier: Programming Language :: Python :: 3.7
Classifier: Programming Language :: Python :: 3.8
Classifier: Programming Language :: Python :: 3.9
Classifier: Programming Language :: Python :: 3.10
Classifier: Topic :: Software Development :: Testing
License-File: LICENSE
License-File: NOTICE.md
Requires-Dist: webtest
Requires-Dist: aiohttp
Requires-Dist: sanic
